doxmlparser/__init__.py
doxmlparser/compound.py
doxmlparser/index.py
doxmlparser-1.16.1.dist-info/licenses/LICENSE
doxmlparser-1.16.1.dist-info/METADATA
doxmlparser-1.16.1.dist-info/WHEEL
doxmlparser-1.16.1.dist-info/top_level.txt
doxmlparser-1.16.1.dist-info/RECORD
