Metadata-Version: 2.4
Name: doxmlparser
Version: 1.16.1
Summary: Python API to access doxygen generated XML output
Home-page: https://github.com/doxygen/doxygen/addon/doxmlparser
Author: Dimitri van Heesch
Author-email: doxygen@gmail.com
License: Copyright 2021 Dimitri van Heesch
License-File: LICENSE
Requires-Dist: lxml>=4.0.0
Requires-Dist: six>=1.0.0
Dynamic: author
Dynamic: author-email
Dynamic: description
Dynamic: home-page
Dynamic: license
Dynamic: license-file
Dynamic: requires-dist
Dynamic: summary
